dph_openai_completion_base/__init__.py
dph_openai_completion_base/abstract_callback.py
dph_openai_completion_base/abstract_callback_factory.py
dph_openai_completion_base/assistant_response.py
dph_openai_completion_base/openai_api_base.py
dph_openai_completion_base/openai_db_connector_base.py
dph_openai_completion_base-0.1.16.dist-info/METADATA
dph_openai_completion_base-0.1.16.dist-info/WHEEL
dph_openai_completion_base-0.1.16.dist-info/licenses/LICENSE
dph_openai_completion_base-0.1.16.dist-info/RECORD
