Metadata-Version: 2.4
Name: dph_openai_completion_base
Version: 0.1.16
Summary: Base building blocks for DP OpenAI completion flows (callbacks, API base, DB connector).
Project-URL: Homepage, https://example.com/
Project-URL: Repository, https://example.com/repo
Author-email: Roman Drogolov <roman.drogolov@vista.com>
License-File: LICENSE
Keywords: async,callbacks,llm,openai
Classifier: License :: OSI Approved :: MIT License
Classifier: Operating System :: OS Independent
Classifier: Programming Language :: Python :: 3
Classifier: Programming Language :: Python :: 3 :: Only
Requires-Python: >=3.10
Requires-Dist: openai==1.74.0
Requires-Dist: pydantic>=2.0
